MANIFEST.in
README.md
setup.py
blmfilter/__init__.py
blmfilter.egg-info/PKG-INFO
blmfilter.egg-info/SOURCES.txt
blmfilter.egg-info/dependency_links.txt
blmfilter.egg-info/top_level.txt
blmfilter/internal/__init__.py
blmfilter/internal/interface/__init__.py
blmfilter/internal/interface/bloomfilter.py
blmfilter/pkg/__init__.py
blmfilter/pkg/bitmap/__init__.py
blmfilter/pkg/version/__init__.py
demo/__init__.py